AZMusicAPI/__init__.py
MusicAPI/AZMusicAPI.py
MusicAPI/MusicAPI.py
MusicAPI/__init__.py
AZMusicAPI-1.6.0.dist-info/METADATA
AZMusicAPI-1.6.0.dist-info/WHEEL
AZMusicAPI-1.6.0.dist-info/top_level.txt
AZMusicAPI-1.6.0.dist-info/RECORD
