Metadata-Version: 2.1
Name: AZMusicAPI
Version: 1.6.0
Summary: 轻松访问音乐信息和歌曲音频链接 | Easy access to music information and song audio links
Author: AZ Studio
Project-URL: GitHub, https://github.com/AZ-Studio-2023/AZMusicAPI/
Requires-Dist: requests
Requires-Dist: bilibili-api-python
